Neutron/__init__.py
Neutron/elements.py
neutron_web-0.5.1.dist-info/LICENSE
neutron_web-0.5.1.dist-info/METADATA
neutron_web-0.5.1.dist-info/WHEEL
neutron_web-0.5.1.dist-info/top_level.txt
neutron_web-0.5.1.dist-info/RECORD
