Metadata-Version: 2.1
Name: neutron-web
Version: 0.5.1
Summary: Create modern cross-platform apps in Python using HTML and CSS
Author: IanTerzo (Ian Baldelli)
Author-email: ian.baldelli@gmail.com
Keywords: python,HTML,CSS,GUI,desktop apps
Classifier: Development Status :: 4 - Beta
Classifier: Intended Audience :: Developers
Classifier: Programming Language :: Python :: 3
Classifier: Operating System :: Unix
Classifier: Operating System :: MacOS :: MacOS X
Classifier: Operating System :: Microsoft :: Windows
License-File: LICENSE
Requires-Dist: PyQt6
Requires-Dist: PyQt6-WebEngine
Requires-Dist: asyncio
Requires-Dist: bs4
Requires-Dist: websockets
